{
  "hosts": [
    {
      "host": "edge.example.com",
      "host-metadata":
      {
        "generic-metadata-type": "MI.ResponseMetadata",
        "generic-metadata-value": {
          "headers": [
                    {
                      "header-name": "X-Custom-Response-1",
                      "header-value": "test1"
                    },
                    {
                      "header-name": "X-Custom-Response-2",
                      "header-value": "test2"
                    }
                  ]
          }
      },
      "paths": [
        {
          "path-pattern": {
            "pattern": "/videos/trailers/*"
          }
        }
      ]
    }
  ]
}